LICENSE
MANIFEST.in
Makefile
README.rst
setup.cfg
setup.py
mangopay/__init__.py
mangopay/__init__.pyc
mangopay/api.py
mangopay/api.pyc
mangopay/base.py
mangopay/base.pyc
mangopay/compat.py
mangopay/compat.pyc
mangopay/constants.py
mangopay/constants.pyc
mangopay/exceptions.py
mangopay/exceptions.pyc
mangopay/fields.py
mangopay/fields.pyc
mangopay/query.py
mangopay/query.pyc
mangopay/resources.py
mangopay/resources.pyc
mangopay/signals.py
mangopay/signals.pyc
mangopay/utils.py
mangopay/utils.pyc
python_mangopay.egg-info/PKG-INFO
python_mangopay.egg-info/SOURCES.txt
python_mangopay.egg-info/dependency_links.txt
python_mangopay.egg-info/entry_points.txt
python_mangopay.egg-info/pbr.json
python_mangopay.egg-info/requires.txt
python_mangopay.egg-info/top_level.txt
tests/__init__.py
tests/__init__.pyc
tests/credentials.py
tests/credentials.pyc
tests/mocks.py
tests/mocks.pyc
tests/resources.py
tests/resources.pyc
tests/settings.py
tests/settings.pyc
tests/test_bankaccounts.py
tests/test_bankaccounts.pyc
tests/test_base.py
tests/test_base.pyc
tests/test_cards.py
tests/test_cards.pyc
tests/test_kycs.py
tests/test_kycs.pyc
tests/test_notifications.py
tests/test_notifications.pyc
tests/test_payins.py
tests/test_payins.pyc
tests/test_payouts.py
tests/test_payouts.pyc
tests/test_preauthorizations.py
tests/test_preauthorizations.pyc
tests/test_refunds.py
tests/test_refunds.pyc
tests/test_transactions.py
tests/test_transactions.pyc
tests/test_transfers.py
tests/test_transfers.pyc
tests/test_users.py
tests/test_users.pyc
tests/test_wallets.py
tests/test_wallets.pyc
tests/fixtures/card.json
tests/fixtures/cardregistrations.json
tests/fixtures/cardregistrations_update.json
tests/fixtures/legal_user.json
tests/fixtures/legal_user_wallet.json
tests/fixtures/legal_user_wallet_89.json
tests/fixtures/legal_user_wallet_99.json
tests/fixtures/natural_user.json
tests/fixtures/natural_user_wallet.json
tests/fixtures/natural_user_wallet_9.json
tests/fixtures/user_list_2_per_page.json
tests/fixtures/user_list_2_per_page_page1.json
tests/fixtures/user_list_3_per_page_page2.json
tests/fixtures/user_list_full.json
tests/fixtures/user_list_page1.json
tests/fixtures/user_wallet.json
tests/images/image.jpg