Metadata-Version: 1.1
Name: python-mangopay
Version: 1.0.0a0
Summary: A client library written in python to work with mangopay v2 api
Home-page: https://github.com/ulule/python-mangopay
Author: Ulule
Author-email: tech@ulule.com
License: MIT
Keywords: mangopay api development
Platform: UNKNOWN
Classifier: Intended Audience :: Developers
Classifier: Topic :: Software Development :: Build Tools
Classifier: License :: OSI Approved :: MIT License
Classifier: Programming Language :: Python :: 2
Classifier: Programming Language :: Python :: 2.7
Classifier: Programming Language :: Python :: 3
Classifier: Programming Language :: Python :: 3.4
